{
  "name": "Test Circle",
  "description": "A simple circle shader",
  "meta_info": {
    "category": "visual",
    "tags": [
      "circle",
      "basic"
    ],
    "complexity": "low"
  },
  "vertex_shader": "void main() { gl_Position = vec4(position, 1.0); }",
  "fragment_shader": "uniform vec2 u_resolution; uniform float u_time; uniform float u_gridSize; uniform vec3 u_gridColor; uniform float u_radius; void main() { vec2 st = gl_FragCoord.xy/u_resolution.xy; st = st * 2.0 - 1.0; st.x *= u_resolution.x/u_resolution.y; float d = length(st) - u_radius; gl_FragColor = vec4(vec3(1.0 - smoothstep(0.0, 0.01, d)), 1.0); }",
  "shader_lib_id": 1,
  "uniforms": [
    {
      "name": "u_time",
      "type": "float",
      "stage": "fragment",
      "default": 0.0
    },
    {
      "name": "u_resolution",
      "type": "vec2",
      "stage": "fragment",
      "default": [
        800,
        600
      ]
    },
    {
      "name": "u_backgroundColor",
      "type": "vec3",
      "stage": "fragment",
      "default": "#1a1a1a"
    },
    {
      "name": "u_gridSize",
      "type": "float",
      "stage": "fragment",
      "default": 0.0
    },
    {
      "name": "u_gridColor",
      "type": "vec3",
      "stage": "fragment",
      "default": [
        0.9,
        0.9,
        0.9
      ]
    },
    {
      "name": "u_radius",
      "type": "float",
      "stage": "fragment",
      "default": 0.5
    }
  ],
  "input_parameters": [
    {
      "name": "radius",
      "parameter": "u_radius",
      "path": "u_radius",
      "type": "float",
      "default": 0.5,
      "min": 0.1,
      "max": 1.0
    }
  ]
}
